noesis/__init__.py
noesis/communities.py
noesis/io.py
noesis/layout.py
noesis/links.py
noesis/models.py
noesis/network.py
noesis/nodes.py
noesis/utils.py
noesis/data/karate.gml
noesis/data/noesis-analyzer.lsp.201708.jar
noesis/data/noesis-logo.png
noesis/tests/__init_.py
noesis/tests/test.py
noesis-0.2.8.dist-info/METADATA
noesis-0.2.8.dist-info/RECORD
noesis-0.2.8.dist-info/WHEEL
noesis-0.2.8.dist-info/top_level.txt
