Metadata-Version: 2.1
Name: noesis
Version: 0.2.8
Summary: An open source framework for network data mining that provides a large collection of network analysis techniques
Home-page: http://noesis.ikor.org/
Author: The NOESIS project team
Author-email: noesis-support@ikor.org
License: MIT
Keywords: noesis,network
Platform: UNKNOWN
Requires-Dist: numpy
Requires-Dist: javabridge
